drpython/__init__.py
drpython/email/__init__.py
drpython/email/_noti.py
drpython/telegram/__init__.py
drpython/telegram/_noti.py
drpython-0.1.5.dist-info/METADATA
drpython-0.1.5.dist-info/WHEEL
drpython-0.1.5.dist-info/RECORD
